rawtools/__init__.py
rawtools/cli.py
rawtools/convert.py
rawtools/dat.py
rawtools/generate.py
rawtools/log.py
rawtools/nsiefx.py
rawtools/nsihdr.py
rawtools/qualitycontrol.py
rawtools/raw2img.py
rawtools/rawtools.py
rawtools/assets/OpenSans-Regular.ttf
rawtools/gui/__init__.py
rawtools/gui/nsihdr.py
rawtools/lib/win32/efX-SDK-Static.lib
rawtools/lib/win32/efX-SDK.dll
rawtools/lib/win32/efX-SDK.lib
rawtools/lib/win64/efX-SDK-Static.lib
rawtools/lib/win64/efX-SDK.dll
rawtools/lib/win64/efX-SDK.lib
rawtools-0.5.0.dist-info/AUTHORS.rst
rawtools-0.5.0.dist-info/LICENSE
rawtools-0.5.0.dist-info/METADATA
rawtools-0.5.0.dist-info/WHEEL
rawtools-0.5.0.dist-info/entry_points.txt
rawtools-0.5.0.dist-info/top_level.txt
rawtools-0.5.0.dist-info/RECORD
