Metadata-Version: 2.1
Name: rawtools
Version: 0.5.0
Summary: Utility library for consuming and manipulating x-ray data in RAW format
Home-page: https://github.com/Topp-Roots-Lab/python-rawtools
Author: Tim Parker
Author-email: tparker@danforthcenter.com
Keywords: rawtools
Classifier: Development Status :: 2 - Pre-Alpha
Classifier: Intended Audience :: Developers
Classifier: Natural Language :: English
Classifier: Programming Language :: Python :: 3
Classifier: Programming Language :: Python :: 3.10
Requires-Python: >=3.10
License-File: LICENSE
License-File: AUTHORS.rst
Requires-Dist: numpy
Requires-Dist: tqdm
Requires-Dist: Pillow
Requires-Dist: ttkthemes
